distributions/Binomialdistribution.py
distributions/Gaussiandistribution.py
distributions/Generaldistribution.py
distributions/__init__.py
zzhprob_second-0.3.dist-info/METADATA
zzhprob_second-0.3.dist-info/WHEEL
zzhprob_second-0.3.dist-info/top_level.txt
zzhprob_second-0.3.dist-info/RECORD
