Metadata-Version: 2.1
Name: zzhprob-second
Version: 0.3
Summary: Gaussian distributions
Home-page: UNKNOWN
Author: UNKNOWN
Author-email: UNKNOWN
License: UNKNOWN
Platform: UNKNOWN
